migrate/__init__.py
migrate/exceptions.py
migrate/changeset/__init__.py
migrate/changeset/ansisql.py
migrate/changeset/constraint.py
migrate/changeset/schema.py
migrate/changeset/util.py
migrate/changeset/databases/__init__.py
migrate/changeset/databases/firebird.py
migrate/changeset/databases/ibmdb2.py
migrate/changeset/databases/mysql.py
migrate/changeset/databases/oracle.py
migrate/changeset/databases/postgres.py
migrate/changeset/databases/sqlite.py
migrate/changeset/databases/visitor.py
migrate/tests/__init__.py
migrate/tests/changeset/__init__.py
migrate/tests/changeset/test_changeset.py
migrate/tests/changeset/test_constraint.py
migrate/tests/changeset/databases/__init__.py
migrate/tests/changeset/databases/test_ibmdb2.py
migrate/tests/fixture/__init__.py
migrate/tests/fixture/base.py
migrate/tests/fixture/database.py
migrate/tests/fixture/models.py
migrate/tests/fixture/pathed.py
migrate/tests/fixture/shell.py
migrate/tests/fixture/warnings.py
migrate/tests/integrated/__init__.py
migrate/tests/integrated/test_docs.py
migrate/tests/versioning/__init__.py
migrate/tests/versioning/test_api.py
migrate/tests/versioning/test_cfgparse.py
migrate/tests/versioning/test_database.py
migrate/tests/versioning/test_genmodel.py
migrate/tests/versioning/test_keyedinstance.py
migrate/tests/versioning/test_pathed.py
migrate/tests/versioning/test_repository.py
migrate/tests/versioning/test_runchangeset.py
migrate/tests/versioning/test_schema.py
migrate/tests/versioning/test_schemadiff.py
migrate/tests/versioning/test_script.py
migrate/tests/versioning/test_shell.py
migrate/tests/versioning/test_template.py
migrate/tests/versioning/test_util.py
migrate/tests/versioning/test_version.py
migrate/versioning/__init__.py
migrate/versioning/api.py
migrate/versioning/cfgparse.py
migrate/versioning/config.py
migrate/versioning/genmodel.py
migrate/versioning/migrate_repository.py
migrate/versioning/pathed.py
migrate/versioning/repository.py
migrate/versioning/schema.py
sqlalchemy_migrate-0.12.0.dist-info/AUTHORS
sqlalchemy_migrate-0.12.0.dist-info/COPYING
sqlalchemy_migrate-0.12.0.dist-info/METADATA
sqlalchemy_migrate-0.12.0.dist-info/WHEEL
sqlalchemy_migrate-0.12.0.dist-info/entry_points.txt
sqlalchemy_migrate-0.12.0.dist-info/pbr.json
sqlalchemy_migrate-0.12.0.dist-info/top_level.txt
sqlalchemy_migrate-0.12.0.dist-info/RECORD
